nitnem/__init__.py
nitnem/__main__.py
nitnem/cli.py
nitnem/nitnemplay.py
nitnem/assets/JapjiSahibBhaiHarbansSin.mp3
nitnem/assets/RehrasSahib-BhaiHarbansSinghJi.mp3
nitnem/assets/SukhmaniSahibBhaiHarbans.mp3
nitnem-0.3.5.dist-info/licenses/LICENSE
nitnem-0.3.5.dist-info/METADATA
nitnem-0.3.5.dist-info/WHEEL
nitnem-0.3.5.dist-info/entry_points.txt
nitnem-0.3.5.dist-info/top_level.txt
nitnem-0.3.5.dist-info/RECORD
