Metadata-Version: 2.4
Name: nitnem
Version: 0.3.5
Summary: Nitnem using python for Mac and possibly windows latter
Author: Sukhbinder Singh
License: Apache-2.0
Project-URL: Homepage, https://github.com/sukhbinder/nitnem
Project-URL: Changelog, https://github.com/sukhbinder/nitnem/releases
Project-URL: Issues, https://github.com/sukhbinder/nitnem/issues
Project-URL: CI, https://github.com/sukhbinder/nitnem/actions
Classifier: License :: OSI Approved :: Apache Software License
Requires-Python: >=3.7
License-File: LICENSE
Requires-Dist: afplay-win; sys_platform == "win32"
Provides-Extra: test
Requires-Dist: pytest; extra == "test"
Dynamic: license-file
